openzeppelin/__init__.py
openzeppelin/access/accesscontrol/IAccessControl.cairo
openzeppelin/access/accesscontrol/library.cairo
openzeppelin/access/ownable/library.cairo
openzeppelin/account/IAccount.cairo
openzeppelin/account/library.cairo
openzeppelin/account/presets/Account.cairo
openzeppelin/account/presets/AddressRegistry.cairo
openzeppelin/account/presets/EthAccount.cairo
openzeppelin/introspection/erc165/IERC165.cairo
openzeppelin/introspection/erc165/library.cairo
openzeppelin/security/initializable/library.cairo
openzeppelin/security/pausable/library.cairo
openzeppelin/security/reentrancyguard/library.cairo
openzeppelin/security/safemath/library.cairo
openzeppelin/token/erc1155/IERC1155.cairo
openzeppelin/token/erc1155/IERC1155MetadataURI.cairo
openzeppelin/token/erc1155/IERC1155Receiver.cairo
openzeppelin/token/erc1155/library.cairo
openzeppelin/token/erc1155/presets/ERC1155MintableBurnable.cairo
openzeppelin/token/erc1155/presets/utils/ERC1155Holder.cairo
openzeppelin/token/erc20/IERC20.cairo
openzeppelin/token/erc20/library.cairo
openzeppelin/token/erc20/presets/ERC20.cairo
openzeppelin/token/erc20/presets/ERC20Burnable.cairo
openzeppelin/token/erc20/presets/ERC20Mintable.cairo
openzeppelin/token/erc20/presets/ERC20Pausable.cairo
openzeppelin/token/erc20/presets/ERC20Upgradeable.cairo
openzeppelin/token/erc721/IERC721.cairo
openzeppelin/token/erc721/IERC721Metadata.cairo
openzeppelin/token/erc721/IERC721Receiver.cairo
openzeppelin/token/erc721/library.cairo
openzeppelin/token/erc721/enumerable/IERC721Enumerable.cairo
openzeppelin/token/erc721/enumerable/library.cairo
openzeppelin/token/erc721/enumerable/presets/ERC721EnumerableMintableBurnable.cairo
openzeppelin/token/erc721/presets/ERC721MintableBurnable.cairo
openzeppelin/token/erc721/presets/ERC721MintablePausable.cairo
openzeppelin/token/erc721/presets/utils/ERC721Holder.cairo
openzeppelin/upgrades/library.cairo
openzeppelin/upgrades/presets/Proxy.cairo
openzeppelin/utils/constants/library.cairo
openzeppelin_cairo_contracts-0.6.1.dist-info/LICENSE
openzeppelin_cairo_contracts-0.6.1.dist-info/METADATA
openzeppelin_cairo_contracts-0.6.1.dist-info/WHEEL
openzeppelin_cairo_contracts-0.6.1.dist-info/top_level.txt
openzeppelin_cairo_contracts-0.6.1.dist-info/RECORD
