Metadata-Version: 2.1
Name: openzeppelin-cairo-contracts
Version: 0.6.1
Summary: Library for secure smart contract development written in Cairo
Home-page: https://github.com/OpenZeppelin/cairo-contracts
Author: OpenZeppelin Community
Author-email: maintainers@openzeppelin.org
License: MIT
Platform: any
Classifier: Operating System :: OS Independent
Provides-Extra: testing
License-File: LICENSE
